nbval/__init__.py
nbval/_cover4.py
nbval/_cover5.py
nbval/_version.py
nbval/cover.py
nbval/kernel.py
nbval/nbdime_reporter.py
nbval/plugin.py
nbval-0.11.0.dist-info/LICENSE
nbval-0.11.0.dist-info/METADATA
nbval-0.11.0.dist-info/WHEEL
nbval-0.11.0.dist-info/entry_points.txt
nbval-0.11.0.dist-info/top_level.txt
nbval-0.11.0.dist-info/RECORD
