Metadata-Version: 2.1
Name: nbval
Version: 0.11.0
Summary: A py.test plugin to validate Jupyter notebooks
Home-page: https://github.com/computationalmodelling/nbval
Author: Laslett, Cortes, Fauske, Kluyver, Pepper, Fangohr
Classifier: Framework :: IPython
Classifier: Framework :: Pytest
Classifier: License :: OSI Approved :: BSD License
Classifier: Programming Language :: Python :: 3
Classifier: Topic :: Software Development :: Testing
Requires-Python: >=3.7, <4
License-File: LICENSE
Requires-Dist: pytest>=7
Requires-Dist: jupyter_client
Requires-Dist: nbformat
Requires-Dist: ipykernel
Requires-Dist: coverage
